MANIFEST.in
README.rst
setup.py
docs/HISTORY.rst
docs/INSTALL.txt
docs/LICENSE.GPL
docs/LICENSE.txt
redturtle/__init__.py
redturtle.portlet.collection.egg-info/PKG-INFO
redturtle.portlet.collection.egg-info/SOURCES.txt
redturtle.portlet.collection.egg-info/dependency_links.txt
redturtle.portlet.collection.egg-info/entry_points.txt
redturtle.portlet.collection.egg-info/namespace_packages.txt
redturtle.portlet.collection.egg-info/not-zip-safe
redturtle.portlet.collection.egg-info/requires.txt
redturtle.portlet.collection.egg-info/top_level.txt
redturtle/portlet/__init__.py
redturtle/portlet/collection/__init__.py
redturtle/portlet/collection/configure.zcml
redturtle/portlet/collection/rtcollectionportlet.pt
redturtle/portlet/collection/rtcollectionportlet.py
redturtle/portlet/collection/skins.zcml
redturtle/portlet/collection/upgrades.py
redturtle/portlet/collection/upgrades.zcml
redturtle/portlet/collection/Extensions/install.py
redturtle/portlet/collection/css/rtpc.css
redturtle/portlet/collection/locales/i18n.sh
redturtle/portlet/collection/locales/plone.pot
redturtle/portlet/collection/locales/redturtle.portlet.collection-manual.pot
redturtle/portlet/collection/locales/redturtle.portlet.collection.pot
redturtle/portlet/collection/locales/it/LC_MESSAGES/plone.po
redturtle/portlet/collection/locales/it/LC_MESSAGES/redturtle.portlet.collection.po
redturtle/portlet/collection/profiles/default/cssregistry.xml
redturtle/portlet/collection/profiles/default/metadata.xml
redturtle/portlet/collection/profiles/default/portlets.xml
redturtle/portlet/collection/profiles/default/rolemap.xml
redturtle/portlet/collection/profiles/default/skins.xml
redturtle/portlet/collection/profiles/uninstall/cssregistry.xml
redturtle/portlet/collection/profiles/uninstall/skins.xml
redturtle/portlet/collection/skins/customizable_collection_portlet/base_collection_portlet_view.pt
redturtle/portlet/collection/tests/__init__.py
redturtle/portlet/collection/tests/base.py
redturtle/portlet/collection/tests/test_portlet.py